cocoindex/__init__.py
cocoindex/_engine.abi3.so
cocoindex/_internal/datatype.py
cocoindex/_version.py
cocoindex/_version_check.py
cocoindex/auth_registry.py
cocoindex/cli.py
cocoindex/engine_object.py
cocoindex/engine_type.py
cocoindex/engine_value.py
cocoindex/flow.py
cocoindex/functions/__init__.py
cocoindex/functions/_engine_builtin_specs.py
cocoindex/functions/colpali.py
cocoindex/functions/sbert.py
cocoindex/index.py
cocoindex/lib.py
cocoindex/llm.py
cocoindex/op.py
cocoindex/py.typed
cocoindex/query_handler.py
cocoindex/runtime.py
cocoindex/setting.py
cocoindex/setup.py
cocoindex/sources/__init__.py
cocoindex/sources/_engine_builtin_specs.py
cocoindex/subprocess_exec.py
cocoindex/targets/__init__.py
cocoindex/targets/_engine_builtin_specs.py
cocoindex/targets/lancedb.py
cocoindex/tests/__init__.py
cocoindex/tests/test_datatype.py
cocoindex/tests/test_engine_object.py
cocoindex/tests/test_engine_type.py
cocoindex/tests/test_engine_value.py
cocoindex/tests/test_optional_database.py
cocoindex/tests/test_transform_flow.py
cocoindex/tests/test_typing.py
cocoindex/tests/test_validation.py
cocoindex/typing.py
cocoindex/user_app_loader.py
cocoindex/utils.py
cocoindex/validation.py
cocoindex-0.3.25.dist-info/METADATA
cocoindex-0.3.25.dist-info/WHEEL
cocoindex-0.3.25.dist-info/entry_points.txt
cocoindex-0.3.25.dist-info/licenses/THIRD_PARTY_NOTICES.html
cocoindex-0.3.25.dist-info/RECORD
