Metadata-Version: 2.4
Name: cocoindex
Version: 0.3.25
Classifier: Development Status :: 3 - Alpha
Classifier: License :: OSI Approved :: Apache Software License
Classifier: Operating System :: OS Independent
Classifier: Programming Language :: Rust
Classifier: Programming Language :: Python :: 3
Classifier: Programming Language :: Python :: 3 :: Only
Classifier: Programming Language :: Python :: 3.11
Classifier: Programming Language :: Python :: 3.12
Classifier: Programming Language :: Python :: 3.13
Classifier: Programming Language :: Python :: 3.14
Classifier: Topic :: Software Development :: Libraries :: Python Modules
Classifier: Topic :: Text Processing :: Indexing
Classifier: Intended Audience :: Developers
Classifier: Natural Language :: English
Classifier: Typing :: Typed
Requires-Dist: typing-extensions>=4.12
Requires-Dist: click>=8.1.8
Requires-Dist: rich>=14.0.0
Requires-Dist: python-dotenv>=1.1.0
Requires-Dist: watchfiles>=1.1.0
Requires-Dist: numpy>=1.23.2
Requires-Dist: psutil>=7.2.1
Requires-Dist: sentence-transformers>=3.3.1 ; extra == 'all'
Requires-Dist: colpali-engine ; extra == 'all'
Requires-Dist: lancedb>=0.25.0 ; extra == 'all'
Requires-Dist: pyarrow>=19.0.0 ; extra == 'all'
Requires-Dist: colpali-engine ; extra == 'colpali'
Requires-Dist: sentence-transformers>=3.3.1 ; extra == 'embeddings'
Requires-Dist: lancedb>=0.25.0 ; extra == 'lancedb'
Requires-Dist: pyarrow>=19.0.0 ; extra == 'lancedb'
Provides-Extra: all
Provides-Extra: colpali
Provides-Extra: embeddings
Provides-Extra: lancedb
License-File: THIRD_PARTY_NOTICES.html
Summary: With CocoIndex, users declare the transformation, CocoIndex creates & maintains an index, and keeps the derived index up to date based on source update, with minimal computation and changes.
Keywords: indexing,real-time,incremental,pipeline,search,ai,etl,rag,dataflow,context-engineering
Author-email: CocoIndex <cocoindex.io@gmail.com>
License-Expression: Apache-2.0
Requires-Python: >=3.11
Project-URL: Homepage, https://cocoindex.io/
